[
  {
    "parsed": {
      "report_date": "2025-10-18",
      "title": "131 Spamware Extensions Targeting WhatsApp Flood Chrome Web Store",
      "completeness": "Medium",
      "geo": [
        "Brasil",
        "Latam",
        "Portuguese",
        "Brazilian"
      ],
      "ttp_tactics": 2,
      "ttp_techniques": 3,
      "software": [
        "WhatsApp",
        "Chrome",
        "Instagram",
        "TikTok"
      ],
      "languages": [
        "javascript",
        "swift"
      ],
      "links": [
        "https://socket.dev/blog/131-spamware-extensions-targeting-whatsapp-flood-chrome-web-store"
      ]
    }
  }
]